[
  {
    "symbol": "AMD",
    "prev_trend": "Bullish",
    "prev_close": 546.5,
    "price": 518.4299926757812,
    "gap_pct": -5.136323389610018,
    "opt_liq_score": 3,
    "opt_flow_score": 1,
    "opt_total_score": 4,
    "pc_ratio": 0.849948752989409,
    "atm_vol": 27074,
    "atm_oi": 55317,
    "total_score": 6,
    "scenario": "A",
    "pre_source": "last_price"
  },
  {
    "symbol": "NVDA",
    "prev_trend": "Bearish",
    "prev_close": 207.825,
    "price": 201.2949981689453,
    "gap_pct": -3.142067523663985,
    "opt_liq_score": 3,
    "opt_flow_score": 1,
    "opt_total_score": 4,
    "pc_ratio": 0.9284988735365742,
    "atm_vol": 296175,
    "atm_oi": 61588,
    "total_score": 7,
    "scenario": "A",
    "pre_source": "last_price"
  },
  {
    "symbol": "TSLA",
    "prev_trend": "Bearish",
    "prev_close": 403.661,
    "price": 382.5450134277344,
    "gap_pct": -5.231118827993199,
    "opt_liq_score": 3,
    "opt_flow_score": 2,
    "opt_total_score": 5,
    "pc_ratio": 1.5025021057325472,
    "atm_vol": 404064,
    "atm_oi": 39987,
    "total_score": 8,
    "scenario": "A",
    "pre_source": "last_price"
  },
  {
    "symbol": "AAPL",
    "prev_trend": "Bearish",
    "prev_close": 295.65,
    "price": 297.5899963378906,
    "gap_pct": 0.6561800567869602,
    "opt_liq_score": 3,
    "opt_flow_score": 1,
    "opt_total_score": 4,
    "pc_ratio": 0.8078534161696762,
    "atm_vol": 217953,
    "atm_oi": 49866,
    "total_score": 5,
    "scenario": "B",
    "pre_source": "last_price"
  },
  {
    "symbol": "SMCI",
    "prev_trend": "Bullish",
    "prev_close": 36.3197,
    "price": 33.66339874267578,
    "gap_pct": -7.313665193611777,
    "opt_liq_score": 3,
    "opt_flow_score": 1,
    "opt_total_score": 4,
    "pc_ratio": 0.5795961884453922,
    "atm_vol": 23705,
    "atm_oi": 69070,
    "total_score": 6,
    "scenario": "A",
    "pre_source": "last_price"
  },
  {
    "symbol": "MSFT",
    "prev_trend": "Bearish",
    "prev_close": 368.3355,
    "price": 372.989990234375,
    "gap_pct": 1.263655073804989,
    "opt_liq_score": 3,
    "opt_flow_score": 2,
    "opt_total_score": 5,
    "pc_ratio": 0.3223130671386493,
    "atm_vol": 100111,
    "atm_oi": 26284,
    "total_score": 6,
    "scenario": "A",
    "pre_source": "last_price"
  },
  {
    "symbol": "ONDS",
    "prev_trend": "Bearish",
    "prev_close": 8.97,
    "price": 8.755000114440918,
    "gap_pct": -2.3968772080165293,
    "opt_liq_score": 1,
    "opt_flow_score": 1,
    "opt_total_score": 2,
    "pc_ratio": 0.7740222114920329,
    "atm_vol": 3674,
    "atm_oi": 31817,
    "total_score": 5,
    "scenario": "B",
    "pre_source": "last_price"
  },
  {
    "symbol": "RGTI",
    "prev_trend": "Bearish",
    "prev_close": 22.31,
    "price": 21.364999771118164,
    "gap_pct": -4.2357697394972424,
    "opt_liq_score": 2,
    "opt_flow_score": 2,
    "opt_total_score": 4,
    "pc_ratio": 0.29169435215946843,
    "atm_vol": 5832,
    "atm_oi": 13400,
    "total_score": 7,
    "scenario": "A",
    "pre_source": "last_price"
  },
  {
    "symbol": "MU",
    "prev_trend": "Bullish",
    "prev_close": 1230.43,
    "price": 1077.22998046875,
    "gap_pct": -12.450933375425668,
    "opt_liq_score": 3,
    "opt_flow_score": 1,
    "opt_total_score": 4,
    "pc_ratio": 0.6710746203589334,
    "atm_vol": 45998,
    "atm_oi": 51687,
    "total_score": 6,
    "scenario": "A",
    "pre_source": "last_price"
  },
  {
    "symbol": "SNDK",
    "prev_trend": "Bearish",
    "prev_close": 2264.9968,
    "price": 1986.824951171875,
    "gap_pct": -12.281335180170009,
    "opt_liq_score": 3,
    "opt_flow_score": 1,
    "opt_total_score": 4,
    "pc_ratio": 0.607554923344397,
    "atm_vol": 10171,
    "atm_oi": 10514,
    "total_score": 7,
    "scenario": "A",
    "pre_source": "last_price"
  },
  {
    "symbol": "AVGO",
    "prev_trend": "Bearish",
    "prev_close": 392.5,
    "price": 380.1499938964844,
    "gap_pct": -3.146498370322452,
    "opt_liq_score": 3,
    "opt_flow_score": 1,
    "opt_total_score": 4,
    "pc_ratio": 1.1461456102783727,
    "atm_vol": 16036,
    "atm_oi": 9909,
    "total_score": 7,
    "scenario": "A",
    "pre_source": "last_price"
  },
  {
    "symbol": "INTC",
    "prev_trend": "Bullish",
    "prev_close": 139.0,
    "price": 135.49000549316406,
    "gap_pct": -2.525175904198516,
    "opt_liq_score": 3,
    "opt_flow_score": 1,
    "opt_total_score": 4,
    "pc_ratio": 0.7552486966323799,
    "atm_vol": 49828,
    "atm_oi": 62679,
    "total_score": 6,
    "scenario": "A",
    "pre_source": "last_price"
  },
  {
    "symbol": "MUR",
    "prev_trend": "Neutral",
    "prev_close": 35.1,
    "price": 36.13999938964844,
    "gap_pct": 2.9629612240696184,
    "opt_liq_score": 0,
    "opt_flow_score": 1,
    "opt_total_score": 1,
    "pc_ratio": 67.0,
    "atm_vol": 204,
    "atm_oi": 1034,
    "total_score": 3,
    "scenario": "B",
    "pre_source": "last_price"
  }
]