[
  {
    "symbol": "AMD",
    "prev_trend": "Neutral",
    "prev_close": 202.5391,
    "price": 206.8800048828125,
    "gap_pct": 2.143242901154646,
    "opt_liq_score": 3,
    "opt_flow_score": 2,
    "opt_total_score": 5,
    "pc_ratio": 0.35405468567422294,
    "atm_vol": 17382,
    "atm_oi": 51450,
    "total_score": 7,
    "scenario": "A",
    "pre_source": "last_price"
  },
  {
    "symbol": "NVDA",
    "prev_trend": "Bearish",
    "prev_close": 174.86,
    "price": 177.18499755859375,
    "gap_pct": 1.3296337404745144,
    "opt_liq_score": 3,
    "opt_flow_score": 2,
    "opt_total_score": 5,
    "pc_ratio": 0.4653542305572436,
    "atm_vol": 103687,
    "atm_oi": 131397,
    "total_score": 6,
    "scenario": "A",
    "pre_source": "last_price"
  },
  {
    "symbol": "TSLA",
    "prev_trend": "Bearish",
    "prev_close": 371.51,
    "price": 382.3800048828125,
    "gap_pct": 2.925898329200428,
    "opt_liq_score": 3,
    "opt_flow_score": 2,
    "opt_total_score": 5,
    "pc_ratio": 0.30762714107960715,
    "atm_vol": 148179,
    "atm_oi": 78800,
    "total_score": 7,
    "scenario": "A",
    "pre_source": "last_price"
  },
  {
    "symbol": "AAPL",
    "prev_trend": "Neutral",
    "prev_close": 249.8,
    "price": 251.74000549316406,
    "gap_pct": 0.7766234960624704,
    "opt_liq_score": 3,
    "opt_flow_score": 1,
    "opt_total_score": 4,
    "pc_ratio": 1.119313472134185,
    "atm_vol": 43465,
    "atm_oi": 40591,
    "total_score": 5,
    "scenario": "B",
    "pre_source": "last_price"
  },
  {
    "symbol": "SMCI",
    "prev_trend": "Bearish",
    "prev_close": 20.9113,
    "price": 20.625,
    "gap_pct": -1.369116219460295,
    "opt_liq_score": 3,
    "opt_flow_score": 1,
    "opt_total_score": 4,
    "pc_ratio": 1.2969938428105758,
    "atm_vol": 12684,
    "atm_oi": 37821,
    "total_score": 6,
    "scenario": "A",
    "pre_source": "last_price"
  },
  {
    "symbol": "MSFT",
    "prev_trend": "Bearish",
    "prev_close": 383.58,
    "price": 386.1199951171875,
    "gap_pct": 0.6621813225891642,
    "opt_liq_score": 3,
    "opt_flow_score": 1,
    "opt_total_score": 4,
    "pc_ratio": 0.5552166432035038,
    "atm_vol": 19885,
    "atm_oi": 38922,
    "total_score": 5,
    "scenario": "B",
    "pre_source": "last_price"
  },
  {
    "symbol": "ONDS",
    "prev_trend": "Bearish",
    "prev_close": 10.1499,
    "price": 10.145000457763672,
    "gap_pct": -0.04827182766656531,
    "opt_liq_score": 1,
    "opt_flow_score": 2,
    "opt_total_score": 3,
    "pc_ratio": 0.17464461850884827,
    "atm_vol": 4049,
    "atm_oi": 33596,
    "total_score": 4,
    "scenario": "B",
    "pre_source": "last_price"
  },
  {
    "symbol": "RGTI",
    "prev_trend": "Neutral",
    "prev_close": 14.979,
    "price": 15.135000228881836,
    "gap_pct": 1.041459569275898,
    "opt_liq_score": 1,
    "opt_flow_score": 1,
    "opt_total_score": 2,
    "pc_ratio": 0.4508670520231214,
    "atm_vol": 1255,
    "atm_oi": 4917,
    "total_score": 3,
    "scenario": "B",
    "pre_source": "last_price"
  },
  {
    "symbol": "MU",
    "prev_trend": "Bearish",
    "prev_close": 425.5005,
    "price": 424.25,
    "gap_pct": -0.2938891963699192,
    "opt_liq_score": 2,
    "opt_flow_score": 2,
    "opt_total_score": 4,
    "pc_ratio": 0.457206490614063,
    "atm_vol": 9160,
    "atm_oi": 45666,
    "total_score": 5,
    "scenario": "B",
    "pre_source": "last_price"
  },
  {
    "symbol": "SNDK",
    "prev_trend": "Bearish",
    "prev_close": 717.435,
    "price": 734.0250244140625,
    "gap_pct": 2.312408011048047,
    "opt_liq_score": 1,
    "opt_flow_score": 1,
    "opt_total_score": 2,
    "pc_ratio": 0.556036816459123,
    "atm_vol": 2874,
    "atm_oi": 10685,
    "total_score": 4,
    "scenario": "B",
    "pre_source": "last_price"
  },
  {
    "symbol": "AVGO",
    "prev_trend": "Bearish",
    "prev_close": 313.1001,
    "price": 323.6700134277344,
    "gap_pct": 3.3758895087335894,
    "opt_liq_score": 3,
    "opt_flow_score": 2,
    "opt_total_score": 5,
    "pc_ratio": 0.23761248433762389,
    "atm_vol": 10865,
    "atm_oi": 9691,
    "total_score": 7,
    "scenario": "A",
    "pre_source": "last_price"
  },
  {
    "symbol": "INTC",
    "prev_trend": "Bearish",
    "prev_close": 44.2391,
    "price": 44.88010025024414,
    "gap_pct": 1.448945051423153,
    "opt_liq_score": 3,
    "opt_flow_score": 2,
    "opt_total_score": 5,
    "pc_ratio": 0.15695538057742783,
    "atm_vol": 24244,
    "atm_oi": 68364,
    "total_score": 6,
    "scenario": "A",
    "pre_source": "last_price"
  },
  {
    "symbol": "MUR",
    "prev_trend": "Bullish",
    "prev_close": 38.97,
    "price": 38.91999816894531,
    "gap_pct": -0.1283085220802832,
    "opt_liq_score": 0,
    "opt_flow_score": 2,
    "opt_total_score": 2,
    "pc_ratio": 0.21794871794871795,
    "atm_vol": 95,
    "atm_oi": 8980,
    "total_score": 2,
    "scenario": "C",
    "pre_source": "last_price"
  }
]