[
  {
    "symbol": "AMD",
    "prev_trend": "Bullish",
    "prev_close": 217.1414,
    "price": 220.6699981689453,
    "gap_pct": 1.625023219406943,
    "opt_liq_score": 3,
    "opt_flow_score": 2,
    "opt_total_score": 5,
    "pc_ratio": 0.45476636460284514,
    "atm_vol": 28736,
    "atm_oi": 60687,
    "total_score": 8,
    "scenario": "A",
    "pre_source": "last_price"
  },
  {
    "symbol": "NVDA",
    "prev_trend": "Bullish",
    "prev_close": 176.66,
    "price": 176.11000061035156,
    "gap_pct": -0.31133215761826905,
    "opt_liq_score": 3,
    "opt_flow_score": 1,
    "opt_total_score": 4,
    "pc_ratio": 1.3809431923433158,
    "atm_vol": 61695,
    "atm_oi": 113113,
    "total_score": 4,
    "scenario": "B",
    "pre_source": "last_price"
  },
  {
    "symbol": "TSLA",
    "prev_trend": "Bearish",
    "prev_close": 361.2591,
    "price": 358.92999267578125,
    "gap_pct": -0.6447193507980116,
    "opt_liq_score": 3,
    "opt_flow_score": 1,
    "opt_total_score": 4,
    "pc_ratio": 0.549218887133579,
    "atm_vol": 88259,
    "atm_oi": 61049,
    "total_score": 6,
    "scenario": "A",
    "pre_source": "last_price"
  },
  {
    "symbol": "AAPL",
    "prev_trend": "Bullish",
    "prev_close": 255.35,
    "price": 259.32000732421875,
    "gap_pct": 1.554731671908657,
    "opt_liq_score": 3,
    "opt_flow_score": 1,
    "opt_total_score": 4,
    "pc_ratio": 0.6369211370930765,
    "atm_vol": 28561,
    "atm_oi": 36281,
    "total_score": 7,
    "scenario": "A",
    "pre_source": "last_price"
  },
  {
    "symbol": "SMCI",
    "prev_trend": "Bullish",
    "prev_close": 23.2,
    "price": 22.729999542236328,
    "gap_pct": -2.0258640420847898,
    "opt_liq_score": 1,
    "opt_flow_score": 2,
    "opt_total_score": 3,
    "pc_ratio": 0.16142638036809817,
    "atm_vol": 3029,
    "atm_oi": 49741,
    "total_score": 5,
    "scenario": "B",
    "pre_source": "last_price"
  },
  {
    "symbol": "MSFT",
    "prev_trend": "Bullish",
    "prev_close": 373.4,
    "price": 372.46990966796875,
    "gap_pct": -0.24908685914066075,
    "opt_liq_score": 3,
    "opt_flow_score": 1,
    "opt_total_score": 4,
    "pc_ratio": 0.7696718700223001,
    "atm_vol": 11110,
    "atm_oi": 31111,
    "total_score": 4,
    "scenario": "B",
    "pre_source": "last_price"
  },
  {
    "symbol": "ONDS",
    "prev_trend": "Bullish",
    "prev_close": 9.54,
    "price": 9.654999732971191,
    "gap_pct": 1.2054479347085143,
    "opt_liq_score": 1,
    "opt_flow_score": 1,
    "opt_total_score": 2,
    "pc_ratio": 1.0171306209850106,
    "atm_vol": 2826,
    "atm_oi": 30288,
    "total_score": 4,
    "scenario": "B",
    "pre_source": "last_price"
  },
  {
    "symbol": "RGTI",
    "prev_trend": "Bullish",
    "prev_close": 14.1,
    "price": 14.265000343322754,
    "gap_pct": 1.1702152008705975,
    "opt_liq_score": 0,
    "opt_flow_score": 0,
    "opt_total_score": 0,
    "pc_ratio": 0.7737430167597765,
    "atm_vol": 635,
    "atm_oi": 4575,
    "total_score": 2,
    "scenario": "C",
    "pre_source": "last_price"
  },
  {
    "symbol": "MU",
    "prev_trend": "Bullish",
    "prev_close": 364.68,
    "price": 376.6099853515625,
    "gap_pct": 3.2713571765828924,
    "opt_liq_score": 2,
    "opt_flow_score": 2,
    "opt_total_score": 4,
    "pc_ratio": 0.38139971817754814,
    "atm_vol": 8823,
    "atm_oi": 28313,
    "total_score": 7,
    "scenario": "A",
    "pre_source": "last_price"
  },
  {
    "symbol": "SNDK",
    "prev_trend": "Bullish",
    "prev_close": 697.9,
    "price": 718.47998046875,
    "gap_pct": 2.9488437410445654,
    "opt_liq_score": 1,
    "opt_flow_score": 1,
    "opt_total_score": 2,
    "pc_ratio": 0.620293554562859,
    "atm_vol": 2539,
    "atm_oi": 8741,
    "total_score": 5,
    "scenario": "B",
    "pre_source": "last_price"
  },
  {
    "symbol": "AVGO",
    "prev_trend": "Bullish",
    "prev_close": 314.2,
    "price": 311.0299987792969,
    "gap_pct": -1.0089119098354913,
    "opt_liq_score": 2,
    "opt_flow_score": 2,
    "opt_total_score": 4,
    "pc_ratio": 2.690219732873761,
    "atm_vol": 8565,
    "atm_oi": 16136,
    "total_score": 5,
    "scenario": "B",
    "pre_source": "last_price"
  },
  {
    "symbol": "INTC",
    "prev_trend": "Bullish",
    "prev_close": 50.2499,
    "price": 51.04499816894531,
    "gap_pct": 1.5822880621559763,
    "opt_liq_score": 3,
    "opt_flow_score": 2,
    "opt_total_score": 5,
    "pc_ratio": 0.39669169880251676,
    "atm_vol": 13763,
    "atm_oi": 65667,
    "total_score": 8,
    "scenario": "A",
    "pre_source": "last_price"
  },
  {
    "symbol": "MUR",
    "prev_trend": "Bullish",
    "prev_close": 41.06,
    "price": 41.52000045776367,
    "gap_pct": 1.1203128537839007,
    "opt_liq_score": 0,
    "opt_flow_score": 2,
    "opt_total_score": 2,
    "pc_ratio": 1.8571428571428572,
    "atm_vol": 20,
    "atm_oi": 6785,
    "total_score": 4,
    "scenario": "B",
    "pre_source": "last_price"
  }
]