[
  {
    "symbol": "AMD",
    "prev_trend": "Bearish",
    "prev_close": 505.0,
    "price": 528.64501953125,
    "gap_pct": 4.68218208539604,
    "opt_liq_score": 3,
    "opt_flow_score": 2,
    "opt_total_score": 5,
    "pc_ratio": 0.32655374153827305,
    "atm_vol": 43308,
    "atm_oi": 10355,
    "total_score": 7,
    "scenario": "A",
    "pre_source": "last_price"
  },
  {
    "symbol": "NVDA",
    "prev_trend": "Bearish",
    "prev_close": 203.0892,
    "price": 205.8300018310547,
    "gap_pct": 1.349555678516968,
    "opt_liq_score": 3,
    "opt_flow_score": 1,
    "opt_total_score": 4,
    "pc_ratio": 0.6652987434061713,
    "atm_vol": 392406,
    "atm_oi": 124923,
    "total_score": 5,
    "scenario": "B",
    "pre_source": "last_price"
  },
  {
    "symbol": "TSLA",
    "prev_trend": "Bearish",
    "prev_close": 370.5,
    "price": 382.71209716796875,
    "gap_pct": 3.296112595942982,
    "opt_liq_score": 3,
    "opt_flow_score": 2,
    "opt_total_score": 5,
    "pc_ratio": 0.4474413609118941,
    "atm_vol": 167110,
    "atm_oi": 95574,
    "total_score": 7,
    "scenario": "A",
    "pre_source": "last_price"
  },
  {
    "symbol": "AAPL",
    "prev_trend": "Neutral",
    "prev_close": 325.9925,
    "price": 327.1050109863281,
    "gap_pct": 0.3412688900291013,
    "opt_liq_score": 3,
    "opt_flow_score": 1,
    "opt_total_score": 4,
    "pc_ratio": 0.8160374476923546,
    "atm_vol": 237821,
    "atm_oi": 69003,
    "total_score": 4,
    "scenario": "B",
    "pre_source": "last_price"
  },
  {
    "symbol": "SMCI",
    "prev_trend": "Bearish",
    "prev_close": 23.95,
    "price": 24.815000534057617,
    "gap_pct": 3.6116932528501797,
    "opt_liq_score": 2,
    "opt_flow_score": 2,
    "opt_total_score": 4,
    "pc_ratio": 0.1791044776119403,
    "atm_vol": 5609,
    "atm_oi": 37086,
    "total_score": 6,
    "scenario": "A",
    "pre_source": "last_price"
  },
  {
    "symbol": "MSFT",
    "prev_trend": "Bullish",
    "prev_close": 401.0232,
    "price": 399.2950134277344,
    "gap_pct": -0.43094428757877334,
    "opt_liq_score": 3,
    "opt_flow_score": 2,
    "opt_total_score": 5,
    "pc_ratio": 0.18283374536464772,
    "atm_vol": 76553,
    "atm_oi": 27822,
    "total_score": 5,
    "scenario": "B",
    "pre_source": "last_price"
  },
  {
    "symbol": "ONDS",
    "prev_trend": "Neutral",
    "prev_close": 6.9499,
    "price": 7.710100173950195,
    "gap_pct": 10.938289384742154,
    "opt_liq_score": 3,
    "opt_flow_score": 2,
    "opt_total_score": 5,
    "pc_ratio": 0.19376420915881779,
    "atm_vol": 18378,
    "atm_oi": 24298,
    "total_score": 7,
    "scenario": "A",
    "pre_source": "last_price"
  },
  {
    "symbol": "RGTI",
    "prev_trend": "Bearish",
    "prev_close": 14.31,
    "price": 15.039999961853027,
    "gap_pct": 5.1013274762615435,
    "opt_liq_score": 1,
    "opt_flow_score": 2,
    "opt_total_score": 3,
    "pc_ratio": 0.40727802037845706,
    "atm_vol": 4834,
    "atm_oi": 8640,
    "total_score": 5,
    "scenario": "B",
    "pre_source": "last_price"
  },
  {
    "symbol": "MU",
    "prev_trend": "Bearish",
    "prev_close": 872.25,
    "price": 945.5900268554688,
    "gap_pct": 8.408142947029951,
    "opt_liq_score": 3,
    "opt_flow_score": 1,
    "opt_total_score": 4,
    "pc_ratio": 0.6043936853869796,
    "atm_vol": 45937,
    "atm_oi": 14497,
    "total_score": 6,
    "scenario": "A",
    "pre_source": "last_price"
  },
  {
    "symbol": "SNDK",
    "prev_trend": "Bearish",
    "prev_close": 1408.24,
    "price": 1540.7349853515625,
    "gap_pct": 9.408551479262234,
    "opt_liq_score": 2,
    "opt_flow_score": 2,
    "opt_total_score": 4,
    "pc_ratio": 0.4785548686244204,
    "atm_vol": 7653,
    "atm_oi": 12683,
    "total_score": 6,
    "scenario": "A",
    "pre_source": "last_price"
  },
  {
    "symbol": "AVGO",
    "prev_trend": "Bearish",
    "prev_close": 379.69,
    "price": 384.0249938964844,
    "gap_pct": 1.1417192700583048,
    "opt_liq_score": 3,
    "opt_flow_score": 1,
    "opt_total_score": 4,
    "pc_ratio": 0.6932312346379278,
    "atm_vol": 17911,
    "atm_oi": 11197,
    "total_score": 5,
    "scenario": "B",
    "pre_source": "last_price"
  },
  {
    "symbol": "INTC",
    "prev_trend": "Bearish",
    "prev_close": 97.55,
    "price": 103.62999725341797,
    "gap_pct": 6.232698363319295,
    "opt_liq_score": 3,
    "opt_flow_score": 1,
    "opt_total_score": 4,
    "pc_ratio": 0.5598158648178296,
    "atm_vol": 55570,
    "atm_oi": 26154,
    "total_score": 6,
    "scenario": "A",
    "pre_source": "last_price"
  },
  {
    "symbol": "MUR",
    "prev_trend": "Neutral",
    "prev_close": 36.83,
    "price": 37.2400016784668,
    "gap_pct": 1.1132274734368683,
    "opt_liq_score": 0,
    "opt_flow_score": 1,
    "opt_total_score": 1,
    "pc_ratio": 0.03571428571428571,
    "atm_vol": 29,
    "atm_oi": 1263,
    "total_score": 2,
    "scenario": "C",
    "pre_source": "last_price"
  }
]